teos10/__init__.py
teos10/constants.py
teos10/gibbs.py
teos10/properties.py
teos10-0.1.dist-info/LICENSE
teos10-0.1.dist-info/METADATA
teos10-0.1.dist-info/WHEEL
teos10-0.1.dist-info/top_level.txt
teos10-0.1.dist-info/RECORD
